{
  "tool": "advocate",
  "kind": "analysis",
  "testDir": "/home/ilian/Projects/ADVOCATE/GoAdvocateTesting/Examples/Simple/MixedDeadlock",
  "testName": "TestMixedDeadlock_MD2_2U",
  "profile": "mixed-quick",
  "runId": "2026-05-04T22-26-14Z",
  "runLabel": "baseline",
  "argv": [
    "../ADVOCATE/advocate/advocate",
    "analysis",
    "-path",
    "/home/ilian/Projects/ADVOCATE/GoAdvocateTesting/Examples/Simple/MixedDeadlock",
    "-exec",
    "TestMixedDeadlock_MD2_2U",
    "-prog",
    "TestMixedDeadlock_MD2_2U",
    "-timeoutRec",
    "5",
    "-timeoutRep",
    "5",
    "-stats",
    "-scen",
    "m",
    "-time"
  ],
  "startedAt": "2026-05-04T22:26:14.841179903Z",
  "endedAt": "2026-05-04T22:26:22.625965567Z",
  "exitCode": 0
}